anyconfig_configobj_backend/__init__.py
anyconfig_configobj_backend/configobj_.py
anyconfig_configobj_backend-0.1.4.dist-info/LICENSE.MIT
anyconfig_configobj_backend-0.1.4.dist-info/METADATA
anyconfig_configobj_backend-0.1.4.dist-info/WHEEL
anyconfig_configobj_backend-0.1.4.dist-info/entry_points.txt
anyconfig_configobj_backend-0.1.4.dist-info/top_level.txt
anyconfig_configobj_backend-0.1.4.dist-info/RECORD
