Metadata-Version: 2.1
Name: anyconfig-configobj-backend
Version: 0.1.4
Summary: Backend module for python-anyconfig to load and dump configobj data
Home-page: https://github.com/ssato/python-anyconfig-configobj-backend
Author: Satoru SATOH
Author-email: satoru.satoh@gmail.com
Maintainer: Satoru SATOH
Maintainer-email: satoru.satoh@gmail.com
License: MIT
Project-URL: CI: Travis, https://travis-ci.org/ssato/python-anyconfig-configobj-backend
Project-URL: Download, https://pypi.python.org/pypi/anyconfig-configobj-backend
Project-URL: Download RPMs, https://copr.fedoraproject.org/coprs/ssato/python-anyconfig/
Project-URL: Bug Tracker, https://github.com/ssato/python-anyconfig-configobj-backend/issues
Project-URL: Source, https://github.com/ssato/python-anyconfig-configobj-backend
Platform: any
Classifier: Development Status :: 4 - Beta
Classifier: Intended Audience :: Developers
Classifier: Programming Language :: Python
Classifier: Programming Language :: Python :: 2
Classifier: Programming Language :: Python :: 3
Classifier: Programming Language :: Python :: 2.7
Classifier: Programming Language :: Python :: 3.6
Classifier: Programming Language :: Python :: 3.7
Classifier: Programming Language :: Python :: 3.8
Classifier: Operating System :: OS Independent
Classifier: Topic :: Software Development :: Libraries :: Python Modules
Classifier: Topic :: Text Processing :: Markup
Classifier: Topic :: Utilities
Classifier: License :: OSI Approved :: MIT License
Requires-Dist: anyconfig
Requires-Dist: configobj
